thesaurus_draft/__init__.py
thesaurus_draft/thesaurus.py
thesaurus_draft-0.1.3.dist-info/METADATA
thesaurus_draft-0.1.3.dist-info/WHEEL
thesaurus_draft-0.1.3.dist-info/top_level.txt
thesaurus_draft-0.1.3.dist-info/RECORD
