Metadata-Version: 2.1
Name: thesaurus-draft
Version: 0.1.3
Summary: Demo library
Home-page: https://thesaurus_draft.readthedocs.io/
Author: Dinar Zayahov
Author-email: dinar.zayaxov@mail.ru
License: MIT
Platform: UNKNOWN
Classifier: Intended Audience :: Developers
Classifier: License :: OSI Approved :: MIT License
Classifier: Programming Language :: Python
Classifier: Programming Language :: Python :: 3
Classifier: Programming Language :: Python :: 3.6
Classifier: Programming Language :: Python :: 3.7
Classifier: Programming Language :: Python :: 3.8
Classifier: Programming Language :: Python :: 3.9
Classifier: Operating System :: OS Independent
Requires-Dist: numpy
Requires-Dist: spacy
Requires-Dist: gensim
Requires-Dist: sklearn
Requires-Dist: matplotlib
